Metadata-Version: 1.1
Name: lambdata-nicpapenburg
Version: 0.0.1
Summary: Learning to upload a package
Home-page: UNKNOWN
Author: Nicholas Papenburg
Author-email: nicpapenburg@gmail.com
License: MIT
Keywords: lambda,bloomtech
Platform: UNKNOWN
Classifier: Development Status :: 5 - Production/Stable
Classifier: Intended Audience :: Education
Classifier: Operating System :: Microsoft :: Windows :: Windows 10
Classifier: License :: OSI Approved :: MIT License
Classifier: Programming Language :: Python :: 3
